vexilpy/__init__.py
vexilpy/__main__.py
vexilpy/backendutils/__init__.py
vexilpy/backendutils/__pycache__/__init__.cpython-312.pyc
vexilpy/backendutils/app/__init__.py
vexilpy/backendutils/app/app.py
vexilpy/backendutils/app/appobject.py
vexilpy/backendutils/app/basinapp.py
vexilpy/backendutils/app/blankslateobject.py
vexilpy/backendutils/app/jsonapp.py
vexilpy/backendutils/app/processes.py
vexilpy/backendutils/app/remoteapp.py
vexilpy/backendutils/app/site.py
vexilpy/backendutils/app/standardappexportobject.py
vexilpy/backendutils/app/supportedtags.py
vexilpy/backendutils/app/supportswith.py
vexilpy/backendutils/app/tagobject.py
vexilpy/backendutils/app/yamlapp.py
vexilpy/backendutils/app/__pycache__/__init__.cpython-312.pyc
vexilpy/backendutils/app/__pycache__/app.cpython-312.pyc
vexilpy/backendutils/app/__pycache__/appobject.cpython-312.pyc
vexilpy/backendutils/app/__pycache__/basinapp.cpython-312.pyc
vexilpy/backendutils/app/__pycache__/blankslateobject.cpython-312.pyc
vexilpy/backendutils/app/__pycache__/jsonapp.cpython-312.pyc
vexilpy/backendutils/app/__pycache__/remoteapp.cpython-312.pyc
vexilpy/backendutils/app/__pycache__/standardappexportobject.cpython-312.pyc
vexilpy/backendutils/app/__pycache__/supportedtags.cpython-312.pyc
vexilpy/backendutils/app/__pycache__/supportswith.cpython-312.pyc
vexilpy/backendutils/app/__pycache__/tagobject.cpython-312.pyc
vexilpy/backendutils/app/__pycache__/yamlapp.cpython-312.pyc
vexilpy/backendutils/basin/__init__.py
vexilpy/backendutils/basin/basinreturnobject.py
vexilpy/backendutils/basin/getval.py
vexilpy/backendutils/basin/object.py
vexilpy/backendutils/basin/__pycache__/__init__.cpython-312.pyc
vexilpy/backendutils/basin/__pycache__/basinreturnobject.cpython-312.pyc
vexilpy/backendutils/basin/__pycache__/getval.cpython-312.pyc
vexilpy/backendutils/basin/__pycache__/object.cpython-312.pyc
vexilpy/backendutils/cli/__init__.py
vexilpy/backendutils/cli/__main__.py
vexilpy-12.0.dist-info/LICENSE
vexilpy-12.0.dist-info/METADATA
vexilpy-12.0.dist-info/WHEEL
vexilpy-12.0.dist-info/top_level.txt
vexilpy-12.0.dist-info/RECORD
